README.md
README.txt
setup.py
tomcom/__init__.py
tomcom.plone.traverseuid.egg-info/PKG-INFO
tomcom.plone.traverseuid.egg-info/SOURCES.txt
tomcom.plone.traverseuid.egg-info/dependency_links.txt
tomcom.plone.traverseuid.egg-info/entry_points.txt
tomcom.plone.traverseuid.egg-info/namespace_packages.txt
tomcom.plone.traverseuid.egg-info/not-zip-safe
tomcom.plone.traverseuid.egg-info/requires.txt
tomcom.plone.traverseuid.egg-info/top_level.txt
tomcom/plone/__init__.py
tomcom/plone/traverseuid/__init__.py
tomcom/plone/traverseuid/browser.py
tomcom/plone/traverseuid/configure.zcml