Metadata-Version: 1.1
Name: tomcom.plone.traverseuid
Version: 4.3.0.1
Summary: UNKNOWN
Home-page: https://pypi.python.org/pypi/tomcom.plone.traverseuid
Author: Kai Hoppert
Author-email: kai.hoppert@tomcom.de
License: GPL version 2
Platform: Any
Classifier: Development Status :: 5 - Production/Stable
Classifier: Environment :: Web Environment
Classifier: Framework :: Plone
Classifier: Framework :: Zope2
Classifier: Intended Audience :: Other Audience
Classifier: Intended Audience :: System Administrators
Classifier: License :: OSI Approved :: GNU General Public License (GPL)
Classifier: Operating System :: OS Independent
Classifier: Programming Language :: Python
Classifier: Topic :: Internet :: WWW/HTTP :: Site Management :: Link Checking
